src/AR_NLP_TopicModling.py
src/__init__.py
ar_nlp_topicmodling-0.0.6.dist-info/METADATA
ar_nlp_topicmodling-0.0.6.dist-info/WHEEL
ar_nlp_topicmodling-0.0.6.dist-info/licenses/LICENSE
ar_nlp_topicmodling-0.0.6.dist-info/RECORD
