Metadata-Version: 2.1
Name: AR_NLP_TopicModling
Version: 0.0.6
Summary: Topic modling package
Author-email: Hisham <20hishamibrahim@gmail.com>
License: MIT License
Classifier: License :: OSI Approved :: MIT License
Classifier: Operating System :: OS Independent
Classifier: Programming Language :: Python :: 3
Requires-Python: >=3.7
Requires-Dist: camel-tools
Requires-Dist: nltk
Requires-Dist: pandas
Requires-Dist: sklearn
